ausweiskopie/__init__.py
ausweiskopie/__main__.py
ausweiskopie/personalize.py
ausweiskopie/redact/__init__.py
ausweiskopie/redact/definitions.py
ausweiskopie/redact/fields.py
ausweiskopie/resources/NotoSans-Regular.ttf
ausweiskopie/resources/__init__.py
ausweiskopie/resources/icon.png
ausweiskopie/resources/icon.svg
ausweiskopie/resources/icon_colored.png
ausweiskopie/resources/npa_2010.jpg
ausweiskopie/resources/npa_2019.jpg
ausweiskopie/resources/npa_2021.png
ausweiskopie/resources/npa_back.png
ausweiskopie/resources/passport.png
ausweiskopie/resources/translations.csv
ausweiskopie/resources/vorläufig_back.jpg
ausweiskopie/resources/vorläufig_front.jpg
ausweiskopie/ui/__init__.py
ausweiskopie/ui/dialogs.py
ausweiskopie/ui/dnd.py
ausweiskopie/ui/elements.py
ausweiskopie/ui/threads.py
ausweiskopie-0.1.4.dist-info/METADATA
ausweiskopie-0.1.4.dist-info/WHEEL
ausweiskopie-0.1.4.dist-info/entry_points.txt
ausweiskopie-0.1.4.dist-info/top_level.txt
ausweiskopie-0.1.4.dist-info/RECORD
