Metadata-Version: 2.2
Name: ausweiskopie
Version: 0.1.4
Summary: Create privacy friendly and legal copies of your Ausweisdokument.
Author-email: "Simon <Varbin> Biewald" <simon@fam-biewald.de>
Project-URL: Homepage, https://github.com/Varbin/ausweiskopie
Project-URL: Repository, https://github.com/Varbin/ausweiskopie.git
Project-URL: Issues, https://github.com/Varbin/ausweiskopie/issues
Keywords: Ausweiskopie,Personalausweis,PAuswG,Datensparsamkeit
Classifier: Development Status :: 4 - Beta
Classifier: Environment :: X11 Applications
Classifier: Environment :: Win32 (MS Windows)
Classifier: Intended Audience :: End Users/Desktop
Classifier: License :: OSI Approved :: Mozilla Public License 2.0 (MPL 2.0)
Classifier: Natural Language :: German
Classifier: Natural Language :: English
Classifier: Operating System :: OS Independent
Classifier: Programming Language :: Python :: 3 :: Only
Classifier: Topic :: Multimedia :: Graphics :: Editors :: Raster-Based
Classifier: Topic :: Multimedia :: Graphics :: Graphics Conversion
Classifier: Topic :: Multimedia :: Graphics :: Viewers
Classifier: Topic :: Office/Business
Classifier: Topic :: Security
Classifier: Topic :: Printing
Classifier: Topic :: Utilities
Classifier: Typing :: Typed
Requires-Python: >=3.7
Requires-Dist: pillow>=8.0.0
Requires-Dist: importlib-resources
Provides-Extra: portals
Requires-Dist: dbus-python; sys_platform == "linux" and extra == "portals"
Requires-Dist: pygobject; sys_platform == "linux" and extra == "portals"
Provides-Extra: modern
Requires-Dist: ttkbootstrap>=1.0; extra == "modern"
